mol_translator/__init__.py
mol_translator/aemol.py
mol_translator/cleaning/__init__.py
mol_translator/cleaning/checks.py
mol_translator/cleaning/sanitize/__init__.py
mol_translator/cleaning/sanitize/charge_ops.py
mol_translator/cleaning/sanitize/rdkit_standardise.py
mol_translator/comp_chem/__init__.py
mol_translator/comp_chem/gaussian/__init__.py
mol_translator/comp_chem/gaussian/gaussian_input.py
mol_translator/comp_chem/gaussian/gaussian_read.py
mol_translator/comp_chem/orca/__init__.py
mol_translator/comp_chem/orca/orca_input.py
mol_translator/comp_chem/orca/orca_read.py
mol_translator/conformer/__init__.py
mol_translator/conformer/aeconf.py
mol_translator/preprocessing/__init__.py
mol_translator/preprocessing/dataframe_converter/__init__.py
mol_translator/preprocessing/dataframe_converter/dataframe_prep.py
mol_translator/preprocessing/dataframe_converter/dataframe_read.py
mol_translator/preprocessing/dataframe_converter/dataframe_write.py
mol_translator/preprocessing/descriptor/__init__.py
mol_translator/preprocessing/descriptor/descriptor_gen.py
mol_translator/preprocessing/descriptor/atom_descriptors/__init__.py
mol_translator/preprocessing/descriptor/atom_descriptors/openbabel_atom_descriptors.py
mol_translator/preprocessing/descriptor/atom_descriptors/rdkit_atom_descriptors.py
mol_translator/preprocessing/descriptor/pair_descriptors/__init__.py
mol_translator/preprocessing/descriptor/pair_descriptors/openbabel_pair_descriptors.py
mol_translator/preprocessing/descriptor/pair_descriptors/rdkit_pair_descriptors.py
mol_translator/properties/__init__.py
mol_translator/properties/property_io.py
mol_translator/properties/binding/__init__.py
mol_translator/properties/binding/binding_read.py
mol_translator/properties/charge/__init__.py
mol_translator/properties/charge/charge_read.py
mol_translator/properties/energy/__init__.py
mol_translator/properties/energy/energy_read.py
mol_translator/properties/nmr/__init__.py
mol_translator/properties/nmr/nmr_ops.py
mol_translator-0.1.0.dist-info/LICENSE
mol_translator-0.1.0.dist-info/METADATA
mol_translator-0.1.0.dist-info/WHEEL
mol_translator-0.1.0.dist-info/top_level.txt
mol_translator-0.1.0.dist-info/RECORD
