Metadata-Version: 2.1
Name: mol-translator
Version: 0.1.0
Summary: Molecule processing package for working with NMR data. Used for pipeline with DFT calculation & machine learning preprocessing
Home-page: https://github.com/Buttsgroup/mol_translator
Author: Calvin Yiu, Will Gerrard, Ben Honore, Butts Research Group
Author-email: calvin.yiu@bristol.ac.uk
License: GNU GENERAL PUBLIC LICENSE
Classifier: Development Status :: 4 - Beta
Classifier: Topic :: Scientific/Engineering :: Chemistry
Classifier: Programming Language :: Python :: 3.9
Requires-Python: ==3.9.*
License-File: LICENSE
Requires-Dist: rdkit-pypi (>=2022.3.2.1)
Requires-Dist: numpy (>=1.22.4)
Requires-Dist: pandas (>=1.4.2)
Requires-Dist: matplotlib (>=3.5.2)
Requires-Dist: scikit-learn (>=1.0.2)
Requires-Dist: tqdm (>=4.64.0)
